multiple_simulations.py
parties.py
post_process.py
simulation.py
parties/__init__.py
parties/multiple_simulations.py
parties/post_process.py
parties/simulation.py
parties-0.0.12.dist-info/DESCRIPTION.rst
parties-0.0.12.dist-info/METADATA
parties-0.0.12.dist-info/RECORD
parties-0.0.12.dist-info/WHEEL
parties-0.0.12.dist-info/metadata.json
parties-0.0.12.dist-info/top_level.txt
